{
  "db_name": "PostgreSQL",
  "query": "\n            SELECT id, key, name, description, template_content,\n                   variables as \"variables: serde_json::Value\",\n                   version, is_active, created_at, updated_at, created_by, updated_by\n            FROM prompts\n            WHERE id = $1\n            ",
  "describe": {
    "columns": [
      {
        "ordinal": 0,
        "name": "id",
        "type_info": "Uuid"
      },
      {
        "ordinal": 1,
        "name": "key",
        "type_info": "Varchar"
      },
      {
        "ordinal": 2,
        "name": "name",
        "type_info": "Varchar"
      },
      {
        "ordinal": 3,
        "name": "description",
        "type_info": "Text"
      },
      {
        "ordinal": 4,
        "name": "template_content",
        "type_info": "Text"
      },
      {
        "ordinal": 5,
        "name": "variables: serde_json::Value",
        "type_info": "Jsonb"
      },
      {
        "ordinal": 6,
        "name": "version",
        "type_info": "Int4"
      },
      {
        "ordinal": 7,
        "name": "is_active",
        "type_info": "Bool"
      },
      {
        "ordinal": 8,
        "name": "created_at",
        "type_info": "Timestamptz"
      },
      {
        "ordinal": 9,
        "name": "updated_at",
        "type_info": "Timestamptz"
      },
      {
        "ordinal": 10,
        "name": "created_by",
        "type_info": "Uuid"
      },
      {
        "ordinal": 11,
        "name": "updated_by",
        "type_info": "Uuid"
      }
    ],
    "parameters": {
      "Left": [
        "Uuid"
      ]
    },
    "nullable": [
      false,
      false,
      false,
      true,
      false,
      true,
      false,
      false,
      false,
      false,
      true,
      true
    ]
  },
  "hash": "a2e5c5a866e72172862bd347f6c593f2bfd74d04f6ddd718ace73f029f63e7ec"
}
